holdup/__init__.py
holdup/__main__.py
holdup/checks.py
holdup/cli.py
holdup/pg.py
holdup-5.1.1.dist-info/AUTHORS.rst
holdup-5.1.1.dist-info/LICENSE
holdup-5.1.1.dist-info/METADATA
holdup-5.1.1.dist-info/WHEEL
holdup-5.1.1.dist-info/entry_points.txt
holdup-5.1.1.dist-info/top_level.txt
holdup-5.1.1.dist-info/RECORD
